<?xml version="1.0" encoding="UTF-8"?>
<objects serializationModel="Studio.02.03.00">
	<object class="AudioFile" id="{c8e42e63-2ac0-4fd8-b597-542775cfbea1}">
		<property name="assetPath">
			<value>SFX/Animal Sound/harimau-220046.mp3</value>
		</property>
		<property name="frequencyInKHz">
			<value>48</value>
		</property>
		<property name="channelCount">
			<value>2</value>
		</property>
		<property name="length">
			<value>1.6799999999999999</value>
		</property>
		<relationship name="masterAssetFolder">
			<destination>{21145dc6-5bb6-4d10-b5ac-6ea9c3e16991}</destination>
		</relationship>
	</object>
</objects>
